opentelemetry/instrumentation/flask/__init__.py
opentelemetry/instrumentation/flask/package.py
opentelemetry/instrumentation/flask/version.py
opentelemetry_instrumentation_flask-0.47b0.dist-info/METADATA
opentelemetry_instrumentation_flask-0.47b0.dist-info/WHEEL
opentelemetry_instrumentation_flask-0.47b0.dist-info/entry_points.txt
opentelemetry_instrumentation_flask-0.47b0.dist-info/licenses/LICENSE
opentelemetry_instrumentation_flask-0.47b0.dist-info/RECORD
