Metadata-Version: 2.3
Name: opentelemetry-instrumentation-flask
Version: 0.47b0
Summary: Flask instrumentation for OpenTelemetry
Project-URL: Homepage, https://github.com/open-telemetry/opentelemetry-python-contrib/tree/main/instrumentation/opentelemetry-instrumentation-flask
Author-email: OpenTelemetry Authors <cncf-opentelemetry-contributors@lists.cncf.io>
License-Expression: Apache-2.0
License-File: LICENSE
Classifier: Development Status :: 4 - Beta
Classifier: Intended Audience :: Developers
Classifier: License :: OSI Approved :: Apache Software License
Classifier: Programming Language :: Python
Classifier: Programming Language :: Python :: 3
Classifier: Programming Language :: Python :: 3.8
Classifier: Programming Language :: Python :: 3.9
Classifier: Programming Language :: Python :: 3.10
Classifier: Programming Language :: Python :: 3.11
Classifier: Programming Language :: Python :: 3.12
Requires-Python: >=3.8
Requires-Dist: importlib-metadata>=4.0
Requires-Dist: opentelemetry-api~=1.12
Requires-Dist: opentelemetry-instrumentation-wsgi==0.47b0
Requires-Dist: opentelemetry-instrumentation==0.47b0
Requires-Dist: opentelemetry-semantic-conventions==0.47b0
Requires-Dist: opentelemetry-util-http==0.47b0
Requires-Dist: packaging>=21.0
Provides-Extra: instruments
Requires-Dist: flask>=1.0; extra == 'instruments'
